lmflux/__init__.py
lmflux/logger.py
lmflux/variables.py
lmflux/agents/__init__.py
lmflux/agents/components.py
lmflux/agents/sessions.py
lmflux/agents/structure.py
lmflux/core/__init__.py
lmflux/core/components.py
lmflux/core/llm_impl.py
lmflux/core/llms.py
lmflux/core/templates.py
lmflux/flow/__init__.py
lmflux/flow/definitions.py
lmflux/flow/toolbox.py
lmflux/metaclasses/__init__.py
lmflux/metaclasses/singleton.py
lmflux-0.0.5.dist-info/METADATA
lmflux-0.0.5.dist-info/WHEEL
lmflux-0.0.5.dist-info/top_level.txt
lmflux-0.0.5.dist-info/RECORD
