Metadata-Version: 2.4
Name: lmflux
Version: 0.0.5
Summary: LmFlux is a declarative Open-Source Agentic framework.
Author-email: Caio Cominato <caiopetrellicominato@gmail.com>
License: MIT
Requires-Python: >=3.11
Requires-Dist: dotenv>=0.9.9
Requires-Dist: jsonpath-ng>=1.7.0
Requires-Dist: openai>=1.95.1
Requires-Dist: unidecode>=1.4.0
